mcp_server_endstone/__init__.py
mcp_server_endstone/cli.py
mcp_server_endstone/server.py
mcp_server_endstone/reference/endstone/__init__.py
mcp_server_endstone/reference/endstone/__main__.py
mcp_server_endstone/reference/endstone/actor.py
mcp_server_endstone/reference/endstone/ban.py
mcp_server_endstone/reference/endstone/block.py
mcp_server_endstone/reference/endstone/boss.py
mcp_server_endstone/reference/endstone/command.py
mcp_server_endstone/reference/endstone/damage.py
mcp_server_endstone/reference/endstone/enchantments.py
mcp_server_endstone/reference/endstone/event.py
mcp_server_endstone/reference/endstone/form.py
mcp_server_endstone/reference/endstone/inventory.py
mcp_server_endstone/reference/endstone/lang.py
mcp_server_endstone/reference/endstone/level.py
mcp_server_endstone/reference/endstone/map.py
mcp_server_endstone/reference/endstone/permissions.py
mcp_server_endstone/reference/endstone/plugin.py
mcp_server_endstone/reference/endstone/scheduler.py
mcp_server_endstone/reference/endstone/scoreboard.py
mcp_server_endstone/reference/endstone/util.py
mcp_server_endstone/reference/endstone/_internal/__init__.py
mcp_server_endstone/reference/endstone/_internal/endstone_python.pyi
mcp_server_endstone/reference/endstone/_internal/metrics.py
mcp_server_endstone/reference/endstone/_internal/plugin_loader.py
mcp_server_endstone/reference/endstone/_internal/bootstrap/__init__.py
mcp_server_endstone/reference/endstone/_internal/bootstrap/base.py
mcp_server_endstone/reference/endstone/_internal/bootstrap/linux.py
mcp_server_endstone/reference/endstone/_internal/bootstrap/windows.py
mcp_server_endstone/reference/endstone/_internal/fonts/JetBrainsMono-Regular.ttf
mcp_server_endstone/reference/endstone/config/endstone.toml
mcp_server_endstone/reference/python-example-plugin/.gitignore
mcp_server_endstone/reference/python-example-plugin/LICENSE
mcp_server_endstone/reference/python-example-plugin/README.md
mcp_server_endstone-0.1.4.dist-info/METADATA
mcp_server_endstone-0.1.4.dist-info/WHEEL
mcp_server_endstone-0.1.4.dist-info/entry_points.txt
mcp_server_endstone-0.1.4.dist-info/top_level.txt
mcp_server_endstone-0.1.4.dist-info/RECORD
