Metadata-Version: 2.4
Name: mcp-server-endstone
Version: 0.1.4
Summary: 一个为 EndstoneMC 开发提供支持的 Model Context Protocol (MCP) 服务器
Author-email: mcayear <mcayear@163.com>
License-Expression: MIT
Project-URL: Homepage, https://github.com/Mcayear/mcp-server-endstone
Project-URL: Bug Tracker, https://github.com/Mcayear/mcp-server-endstone/issues
Classifier: Programming Language :: Python :: 3
Classifier: Operating System :: OS Independent
Requires-Python: >=3.8
Requires-Dist: mcp>=0.1.0
